FlaskRumenjiaochengLihui/README.md
FlaskRumenjiaochengLihui/__init__.py
FlaskRumenjiaochengLihui/__main__.py
FlaskRumenjiaochengLihui/file.epub
FlaskRumenjiaochengLihui/index.html
FlaskRumenjiaochengLihui/css/__init__.py
FlaskRumenjiaochengLihui/css/annotations.css
FlaskRumenjiaochengLihui/css/main.css
FlaskRumenjiaochengLihui/css/normalize.css
FlaskRumenjiaochengLihui/css/popup.css
FlaskRumenjiaochengLihui/font/__init__.py
FlaskRumenjiaochengLihui/font/fontello.eot
FlaskRumenjiaochengLihui/font/fontello.svg
FlaskRumenjiaochengLihui/font/fontello.ttf
FlaskRumenjiaochengLihui/font/fontello.woff
FlaskRumenjiaochengLihui/img/__init__.py
FlaskRumenjiaochengLihui/img/annotator-glyph-sprite.png
FlaskRumenjiaochengLihui/img/annotator-icon-sprite.png
FlaskRumenjiaochengLihui/img/apple-touch-icon.png
FlaskRumenjiaochengLihui/img/cancelfullscreen.png
FlaskRumenjiaochengLihui/img/close.png
FlaskRumenjiaochengLihui/img/fullscreen.png
FlaskRumenjiaochengLihui/img/loader.gif
FlaskRumenjiaochengLihui/img/menu-icon.png
FlaskRumenjiaochengLihui/img/save.png
FlaskRumenjiaochengLihui/img/saved.png
FlaskRumenjiaochengLihui/img/settings-s.png
FlaskRumenjiaochengLihui/img/settings.png
FlaskRumenjiaochengLihui/img/star.png
FlaskRumenjiaochengLihui/js/__init__.py
FlaskRumenjiaochengLihui/js/epub.js
FlaskRumenjiaochengLihui/js/epub.min.js
FlaskRumenjiaochengLihui/js/epub.min.map
FlaskRumenjiaochengLihui/js/hooks.min.js
FlaskRumenjiaochengLihui/js/hooks.min.map
FlaskRumenjiaochengLihui/js/reader.js
FlaskRumenjiaochengLihui/js/reader.js.map
FlaskRumenjiaochengLihui/js/reader.min.js
FlaskRumenjiaochengLihui/js/reader.min.map
FlaskRumenjiaochengLihui/js/hooks/__init__.py
FlaskRumenjiaochengLihui/js/hooks/extensions/__init__.py
FlaskRumenjiaochengLihui/js/hooks/extensions/highlight.js
FlaskRumenjiaochengLihui/js/libs/__init__.py
FlaskRumenjiaochengLihui/js/libs/jquery.min.js
FlaskRumenjiaochengLihui/js/libs/localforage.min.js
FlaskRumenjiaochengLihui/js/libs/screenfull.js
flask_rumenjiaocheng_lihui-2024.3.4.0.dist-info/METADATA
flask_rumenjiaocheng_lihui-2024.3.4.0.dist-info/WHEEL
flask_rumenjiaocheng_lihui-2024.3.4.0.dist-info/entry_points.txt
flask_rumenjiaocheng_lihui-2024.3.4.0.dist-info/top_level.txt
flask_rumenjiaocheng_lihui-2024.3.4.0.dist-info/RECORD
